{
  "title": "AssessedSqlDatabaseV2Operations_Get",
  "operationId": "AssessedSqlDatabaseV2Operations_Get",
  "parameters": {
    "api-version": "2023-04-01-preview",
    "subscriptionId": "2FD69B22-6BC2-4241-82CF-2416BA2BE674",
    "resourceGroupName": "rgmigrate",
    "projectName": "DfF!@Y'GP9K-vj'|2_=5Vm;`t!)1NPGAh4\"yt6\"7^Ikfh5^@L5iFvK$\\njwTd'Bmi5p5Pg0{mYT+8i0tssBF~|Q.L",
    "groupName": "fDMK6Pb(F@G(BOjaDXjHY.5[du F6IR4Xaa%JO-$}.'6u\")!5XT2ve(|t(]zPSz-!D]e~4RQN`Bpo2qfDw|.v^RdqN-4g6XJkS{)z;CX%{!ET",
    "assessmentName": "R]MV1(yG!|dVtCdZMM\\vbDu_|wNnm5tDN2F)-@X-34x%.uyWSL3.Jb4Ncoip$YYbpA3V'c+rzN^F7kmaB1tEaS4SFJov`WNO8,sR1=o\\F^p-OEP{'hcA_J05V",
    "assessedSqlDatabaseName": "|ew@XL(h.gLsOO7S\\=}uF]O\"\"tuu9'zhgE`XQc`wP+S4f`D@! 4hcH|q$e!6W`;O(^oDpXTd0JaM0`@*jv,a9hGXziLG4F$r.ZOaV)~@tM`R~Qy@5_$$oWwM-OBH8VLPrk;|3u,]^Z]0J~1U])tmuKXf}@Kh}Lb^hOhc4xrx1S.*nZVk5Ut`_]1-G{qh;OrT^CNG%6mWQf2*(,)@Tx6"
  },
  "responses": {
    "200": {
      "body": {
        "properties": {
          "recommendedAzureSqlTargetType": "Unknown",
          "recommendedSuitability": "Unknown",
          "bufferCacheSizeInMB": 20,
          "productSupportStatus": {
            "currentVersion": "gxjc",
            "servicePackStatus": "cjpscketd",
            "esuStatus": "hvykhmhyumyviwzkdo",
            "supportStatus": "lhwfmpmowfkjaskhseituusqypli",
            "eta": 7,
            "currentEsuYear": "dsxuqi",
            "mainstreamEndDate": "2024-02-05T08:54:11.356Z",
            "extendedSupportEndDate": "2024-02-05T08:54:11.356Z",
            "extendedSecurityUpdateYear1EndDate": "2024-02-05T08:54:11.356Z",
            "extendedSecurityUpdateYear2EndDate": "2024-02-05T08:54:11.356Z",
            "extendedSecurityUpdateYear3EndDate": "2024-02-05T08:54:11.356Z"
          },
          "azureSqlMISuitabilityDetails": {
            "azureSqlSku": {
              "azureSqlServiceTier": "Unknown",
              "azureSqlComputeTier": "Unknown",
              "azureSqlHardwareGeneration": "Unknown",
              "storageMaxSizeInMB": 13,
              "predictedDataSizeInMB": 26,
              "predictedLogSizeInMB": 10,
              "cores": 26,
              "azureSqlTargetType": "Unknown"
            },
            "replicaAzureSqlSku": [
              {
                "azureSqlServiceTier": "Unknown",
                "azureSqlComputeTier": "Unknown",
                "azureSqlHardwareGeneration": "Unknown",
                "storageMaxSizeInMB": 13,
                "predictedDataSizeInMB": 26,
                "predictedLogSizeInMB": 10,
                "cores": 26,
                "azureSqlTargetType": "Unknown"
              }
            ],
            "sharedResources": {
              "sharedDataDisks": [
                {
                  "diskType": "Unknown",
                  "diskSize": "Unknown",
                  "diskRedundancy": "Unknown",
                  "storageCost": 1,
                  "recommendedSizeInGib": 2,
                  "recommendedThroughputInMbps": 9,
                  "recommendedIops": 10
                }
              ],
              "sharedLogDisks": [
                {
                  "diskType": "Unknown",
                  "diskSize": "Unknown",
                  "diskRedundancy": "Unknown",
                  "storageCost": 1,
                  "recommendedSizeInGib": 2,
                  "recommendedThroughputInMbps": 9,
                  "recommendedIops": 10
                }
              ],
              "sharedTempDbDisks": [
                {
                  "diskType": "Unknown",
                  "diskSize": "Unknown",
                  "diskRedundancy": "Unknown",
                  "storageCost": 1,
                  "recommendedSizeInGib": 2,
                  "recommendedThroughputInMbps": 9,
                  "recommendedIops": 10
                }
              ],
              "numberOfMounts": 19,
              "quorumWitness": {
                "quorumWitnessType": "Unknown"
              }
            },
            "monthlyComputeCost": 18,
            "monthlyStorageCost": 14,
            "costComponents": [
              {
                "name": "Unknown",
                "value": 4,
                "description": "xojoxclykxbcatzseusjbk"
              }
            ],
            "securitySuitability": "Unknown",
            "shouldProvisionReplicas": true,
            "skuReplicationMode": "NotApplicable",
            "migrationGuidelines": [
              {
                "guidelineId": "ugkbtcdsrlrqgybgj",
                "migrationGuidelineCategory": "Unknown",
                "migrationGuidelineContext": [
                  {
                    "contextKey": "gfwigzbvqg",
                    "contextValue": "kojgnocoshabkhdodwybz"
                  }
                ]
              }
            ],
            "recommendationReasonings": [
              {
                "reasoningId": "fdtbznkngryc",
                "reasoningString": "apygswqqbah",
                "reasoningCategory": "bhskc",
                "contextParameters": [
                  {
                    "contextKey": "tcjrmjnh",
                    "contextValue": "fxcmzrcoxwccmemiubsrb"
                  }
                ]
              }
            ],
            "migrationTargetPlatform": "Unknown",
            "suitability": "Unknown",
            "migrationIssues": [
              {
                "issueId": "y",
                "issueCategory": "Issue",
                "impactedObjects": [
                  {
                    "objectName": "etqansjqwdrerccdovqqzb",
                    "objectType": "gilpmvjanxkzntwhs"
                  }
                ]
              }
            ]
          },
          "azureSqlDBSuitabilityDetails": {
            "azureSqlSku": {
              "azureSqlServiceTier": "Unknown",
              "azureSqlComputeTier": "Unknown",
              "azureSqlHardwareGeneration": "Unknown",
              "storageMaxSizeInMB": 13,
              "predictedDataSizeInMB": 26,
              "predictedLogSizeInMB": 10,
              "cores": 26,
              "azureSqlTargetType": "Unknown"
            },
            "replicaAzureSqlSku": [
              {
                "azureSqlServiceTier": "Unknown",
                "azureSqlComputeTier": "Unknown",
                "azureSqlHardwareGeneration": "Unknown",
                "storageMaxSizeInMB": 13,
                "predictedDataSizeInMB": 26,
                "predictedLogSizeInMB": 10,
                "cores": 26,
                "azureSqlTargetType": "Unknown"
              }
            ],
            "sharedResources": {
              "sharedDataDisks": [
                {
                  "diskType": "Unknown",
                  "diskSize": "Unknown",
                  "diskRedundancy": "Unknown",
                  "storageCost": 1,
                  "recommendedSizeInGib": 2,
                  "recommendedThroughputInMbps": 9,
                  "recommendedIops": 10
                }
              ],
              "sharedLogDisks": [
                {
                  "diskType": "Unknown",
                  "diskSize": "Unknown",
                  "diskRedundancy": "Unknown",
                  "storageCost": 1,
                  "recommendedSizeInGib": 2,
                  "recommendedThroughputInMbps": 9,
                  "recommendedIops": 10
                }
              ],
              "sharedTempDbDisks": [
                {
                  "diskType": "Unknown",
                  "diskSize": "Unknown",
                  "diskRedundancy": "Unknown",
                  "storageCost": 1,
                  "recommendedSizeInGib": 2,
                  "recommendedThroughputInMbps": 9,
                  "recommendedIops": 10
                }
              ],
              "numberOfMounts": 19,
              "quorumWitness": {
                "quorumWitnessType": "Unknown"
              }
            },
            "monthlyComputeCost": 18,
            "monthlyStorageCost": 14,
            "costComponents": [
              {
                "name": "Unknown",
                "value": 4,
                "description": "xojoxclykxbcatzseusjbk"
              }
            ],
            "securitySuitability": "Unknown",
            "shouldProvisionReplicas": true,
            "skuReplicationMode": "NotApplicable",
            "migrationGuidelines": [
              {
                "guidelineId": "ugkbtcdsrlrqgybgj",
                "migrationGuidelineCategory": "Unknown",
                "migrationGuidelineContext": [
                  {
                    "contextKey": "gfwigzbvqg",
                    "contextValue": "kojgnocoshabkhdodwybz"
                  }
                ]
              }
            ],
            "recommendationReasonings": [
              {
                "reasoningId": "fdtbznkngryc",
                "reasoningString": "apygswqqbah",
                "reasoningCategory": "bhskc",
                "contextParameters": [
                  {
                    "contextKey": "tcjrmjnh",
                    "contextValue": "fxcmzrcoxwccmemiubsrb"
                  }
                ]
              }
            ],
            "migrationTargetPlatform": "Unknown",
            "suitability": "Unknown",
            "migrationIssues": [
              {
                "issueId": "y",
                "issueCategory": "Issue",
                "impactedObjects": [
                  {
                    "objectName": "etqansjqwdrerccdovqqzb",
                    "objectType": "gilpmvjanxkzntwhs"
                  }
                ]
              }
            ]
          },
          "isDatabaseHighlyAvailable": true,
          "linkedAvailabilityGroupOverview": {
            "availabilityGroupId": "idnoakhmnotlyyxmlnnhgzyrlfopxc",
            "availabilityGroupName": "ubmevdhgpngqenk",
            "sqlAvailabilityGroupSdsArmId": "kmghr",
            "sqlAvailabilityGroupEntityId": "xtz",
            "sqlAvailabilityReplicaId": "vtkytleq"
          },
          "machineArmId": "uacchhctjl",
          "assessedSqlInstanceArmId": "xftadcqrquwnxlwkqagopz",
          "machineName": "hsx",
          "instanceName": "wgwbsqalsvivmzelaodyvjndu",
          "databaseName": "m",
          "databaseSizeInMB": 16,
          "compatibilityLevel": "Unknown",
          "sqlDatabaseSdsArmId": "hyvlprxztjietwktvbjymko",
          "percentageCoresUtilization": 18,
          "megabytesPerSecondOfRead": 13,
          "megabytesPerSecondOfWrite": 10,
          "numberOfReadOperationsPerSecond": 8,
          "numberOfWriteOperationsPerSecond": 17,
          "confidenceRatingInPercentage": 18,
          "sizingCriterion": "PerformanceBased",
          "createdTimestamp": "2024-02-05T08:54:24.475Z",
          "updatedTimestamp": "2024-02-05T08:54:24.475Z"
        },
        "id": "ibb",
        "name": "fyxtoijdpvhmxffqksfxo",
        "type": "hdvdf",
        "systemData": {
          "createdBy": "nepkpfmnfljqxavydnamhogzlgcw",
          "createdByType": "User",
          "createdAt": "2024-02-05T08:53:27.631Z",
          "lastModifiedBy": "dwiyksimd",
          "lastModifiedByType": "User",
          "lastModifiedAt": "2024-02-05T08:53:27.631Z"
        }
      }
    }
  }
}