{
  "title": "ImportSites_Deletejob",
  "operationId": "ImportSites_Deletejob",
  "parameters": {
    "api-version": "2020-02-01",
    "subscriptionId": "19E05D0F-FAA1-489E-B857-027E38ADB4D3",
    "resourceGroupName": "rgmigrate",
    "siteName": "6--7h--8WS4-2bSTeJ",
    "jobName": "K-Fj0GWM0Z8FM8"
  },
  "responses": {
    "200": {
      "body": {
        "type": "lmnrnhqarflzwmkwhwmjzgptj",
        "properties": {
          "blobName": "ytbpkbpctvaolfmqh",
          "errorSasUri": "buebqrpvzbyaolhrsjktjiv",
          "jobState": "Unknown",
          "numberOfMachinesDeleted": 4,
          "deletionConfirmation": true,
          "errors": [
            "yrvpsgguus"
          ],
          "provisioningState": "Succeeded"
        },
        "id": "zbapwhnxpjerg",
        "name": "fcuzv",
        "status": "efihdhrjaxqopotolid",
        "startTime": "yqedubhqeebekiasculvvtohekuzoe",
        "endTime": "qlymmmlvbdmgutrpmujidrundpn",
        "displayName": "kajkoyadlqweqzudmohsulyfovyef"
      }
    }
  }
}