{
  "title": "NetworkFabrics_CommitConfiguration_ABUpdate",
  "operationId": "NetworkFabrics_CommitConfiguration_ABUpdate",
  "parameters": {
    "api-version": "2025-07-15",
    "subscriptionId": "1234ABCD-0A1B-1234-5678-123456ABCDEF",
    "resourceGroupName": "rgmanagednetworkfabric",
    "networkFabricName": "Replace this value with a string matching RegExp ^[a-zA-Z]{1}[a-zA-Z0-9-_]{2,127}$",
    "body": {
      "commitStage": "Start",
      "commitPolicy": "StartCEConfiguration",
      "devices": [
        "ce1"
      ]
    }
  },
  "responses": {
    "200": {
      "body": {
        "resourceId": "/subscriptions/1234ABCD-0A1B-1234-5678-123456ABCDEF/resourcegroups/example-rg/providers/Microsoft.ManagedNetworkFabric/networkDevices/example-device-1",
        "status": "Failed",
        "name": "example-device-1",
        "percentComplete": 71,
        "startTime": "2025-07-01T09:20:25.780Z",
        "endTime": "2025-07-01T09:20:25.780Z",
        "operations": [
          {
            "status": "Failed",
            "percentComplete": 38,
            "startTime": "2025-07-01T09:20:25.772Z",
            "endTime": "2025-07-01T09:20:25.772Z",
            "operations": [],
            "error": {
              "code": "NotReachable"
            }
          }
        ]
      }
    },
    "202": {
      "headers": {
        "location": "https://contoso.com/operationstatus"
      }
    }
  }
}
