{
  "title": "CloudFormationStackSets_CreateOrUpdate",
  "operationId": "CloudFormationStackSets_CreateOrUpdate",
  "parameters": {
    "api-version": "2024-08-01-preview",
    "subscriptionId": "2843BA70-1EDE-4651-840B-330F3525CDEB",
    "resourceGroupName": "rgcloudFormationStackSet",
    "name": "S0zqmn2m(Kl4]RvmtF[Dlw5e(r50!DqFIGm(zPLAjbeAAgKoqs0SR9zA3Q)zfz9zKgQlTBxCYXoTzH8[4NTnYD*ZsybqT[6zdl7U879G*YlGntG(VRcUN[yT0$JPHv9yMq7ya*y^bL)KR^YHgBUBpYk(8mE7Yz5icX2tzP6w0oB@nJfizPgU!@AaNHt^ffxrpIf$wb9kO6c1)(h^WNMtj8ZD@]@0[4kKjURx1xzYm^K",
    "resource": {
      "properties": {
        "awsProperties": {
          "administrationRoleARN": "rmdvvb",
          "autoDeployment": {
            "enabled": true,
            "retainStacksOnAccountRemoval": true
          },
          "callAs": "DELEGATED_ADMIN",
          "capabilities": [
            "edzlvgsbmqfrxq"
          ],
          "description": "ychku",
          "executionRoleName": "ggziftjfyiobbtyglmpux",
          "managedExecution": {
            "active": true
          },
          "operationPreferences": {
            "failureToleranceCount": 30,
            "failureTolerancePercentage": 24,
            "maxConcurrentCount": 23,
            "maxConcurrentPercentage": 4,
            "regionConcurrencyType": "pzmvvfjkmzss",
            "regionOrder": [
              "yobx"
            ]
          },
          "parameters": [
            {
              "parameterKey": "uftll",
              "parameterValue": "jvsbnvubrjxukgvahryapw"
            }
          ],
          "permissionModel": "SELF_MANAGED",
          "stackInstancesGroup": [
            {
              "deploymentTargets": {
                "accountFilterType": "DIFFERENCE",
                "accounts": [
                  "tv"
                ],
                "accountsUrl": "bxbwvwfrvngzzbupzuczh",
                "organizationalUnitIds": [
                  "wilfhsj"
                ]
              },
              "parameterOverrides": [
                {
                  "parameterKey": "uftll",
                  "parameterValue": "jvsbnvubrjxukgvahryapw"
                }
              ],
              "regions": [
                "sudfxaphdlmeknmrl"
              ]
            }
          ],
          "stackSetId": "eprgxta",
          "stackSetName": "wfbbjnyzrttqqwt",
          "tags": [
            {
              "key": "nske",
              "value": "osigtokfggdb"
            }
          ],
          "templateBody": "clksiqqthzaoksizgbfikwfqlau",
          "templateURL": "yjkkwbrpzenq"
        },
        "publicCloudConnectorsResourceId": "aqrgiomytjqlwcdzmxcebhhwxp",
        "awsAccountId": "dwdxottxkuzhwdcgdvnablsl",
        "arn": "vtteythwslwnjjnzibmkijuvh",
        "publicCloudResourceName": "udz",
        "awsSourceSchema": "ghetqyyzhtyeikecbp",
        "awsRegion": "reoexjnuln",
        "awsTags": {
          "key4760": "ayufgquqqrqznwgsjtxgrplg"
        }
      },
      "tags": {
        "key3132": "wwcoluqcehfsqmhtamypmejw"
      },
      "location": "zbg"
    }
  },
  "responses": {
    "200": {
      "body": {
        "properties": {
          "awsProperties": {
            "administrationRoleARN": "rmdvvb",
            "autoDeployment": {
              "enabled": true,
              "retainStacksOnAccountRemoval": true
            },
            "callAs": "DELEGATED_ADMIN",
            "capabilities": [
              "edzlvgsbmqfrxq"
            ],
            "description": "ychku",
            "executionRoleName": "ggziftjfyiobbtyglmpux",
            "managedExecution": {
              "active": true
            },
            "operationPreferences": {
              "failureToleranceCount": 30,
              "failureTolerancePercentage": 24,
              "maxConcurrentCount": 23,
              "maxConcurrentPercentage": 4,
              "regionConcurrencyType": "pzmvvfjkmzss",
              "regionOrder": [
                "yobx"
              ]
            },
            "parameters": [
              {
                "parameterKey": "uftll",
                "parameterValue": "jvsbnvubrjxukgvahryapw"
              }
            ],
            "permissionModel": "SELF_MANAGED",
            "stackInstancesGroup": [
              {
                "deploymentTargets": {
                  "accountFilterType": "DIFFERENCE",
                  "accounts": [
                    "tv"
                  ],
                  "accountsUrl": "bxbwvwfrvngzzbupzuczh",
                  "organizationalUnitIds": [
                    "wilfhsj"
                  ]
                },
                "parameterOverrides": [
                  {
                    "parameterKey": "uftll",
                    "parameterValue": "jvsbnvubrjxukgvahryapw"
                  }
                ],
                "regions": [
                  "sudfxaphdlmeknmrl"
                ]
              }
            ],
            "stackSetId": "eprgxta",
            "stackSetName": "wfbbjnyzrttqqwt",
            "tags": [
              {
                "key": "nske",
                "value": "osigtokfggdb"
              }
            ],
            "templateBody": "clksiqqthzaoksizgbfikwfqlau",
            "templateURL": "yjkkwbrpzenq"
          },
          "publicCloudConnectorsResourceId": "aqrgiomytjqlwcdzmxcebhhwxp",
          "awsAccountId": "dwdxottxkuzhwdcgdvnablsl",
          "arn": "vtteythwslwnjjnzibmkijuvh",
          "publicCloudResourceName": "udz",
          "awsSourceSchema": "ghetqyyzhtyeikecbp",
          "awsRegion": "reoexjnuln",
          "awsTags": {
            "key4760": "ayufgquqqrqznwgsjtxgrplg"
          },
          "provisioningState": "Succeeded"
        },
        "tags": {
          "key3132": "wwcoluqcehfsqmhtamypmejw"
        },
        "location": "zbg",
        "id": "/subscriptions/{subscriptionId}/resourceGroups/{resourceGroupName}/providers/Microsoft.AwsConnector/CloudFormationStackSets/{resourceName}",
        "name": "rtwrlvg",
        "type": "oapobcbnsfhek",
        "systemData": {
          "createdBy": "wgrougdhpxsbwlllkhgylqyz",
          "createdByType": "User",
          "createdAt": "2024-05-13T15:24:50.743Z",
          "lastModifiedBy": "lljqrglsznlclngoh",
          "lastModifiedByType": "User",
          "lastModifiedAt": "2024-05-13T15:24:50.744Z"
        }
      }
    },
    "201": {
      "headers": {
        "Azure-AsyncOperation": "https://contoso.com/operationstatus"
      },
      "body": {
        "properties": {
          "awsProperties": {
            "administrationRoleARN": "rmdvvb",
            "autoDeployment": {
              "enabled": true,
              "retainStacksOnAccountRemoval": true
            },
            "callAs": "DELEGATED_ADMIN",
            "capabilities": [
              "edzlvgsbmqfrxq"
            ],
            "description": "ychku",
            "executionRoleName": "ggziftjfyiobbtyglmpux",
            "managedExecution": {
              "active": true
            },
            "operationPreferences": {
              "failureToleranceCount": 30,
              "failureTolerancePercentage": 24,
              "maxConcurrentCount": 23,
              "maxConcurrentPercentage": 4,
              "regionConcurrencyType": "pzmvvfjkmzss",
              "regionOrder": [
                "yobx"
              ]
            },
            "parameters": [
              {
                "parameterKey": "uftll",
                "parameterValue": "jvsbnvubrjxukgvahryapw"
              }
            ],
            "permissionModel": "SELF_MANAGED",
            "stackInstancesGroup": [
              {
                "deploymentTargets": {
                  "accountFilterType": "DIFFERENCE",
                  "accounts": [
                    "tv"
                  ],
                  "accountsUrl": "bxbwvwfrvngzzbupzuczh",
                  "organizationalUnitIds": [
                    "wilfhsj"
                  ]
                },
                "parameterOverrides": [
                  {
                    "parameterKey": "uftll",
                    "parameterValue": "jvsbnvubrjxukgvahryapw"
                  }
                ],
                "regions": [
                  "sudfxaphdlmeknmrl"
                ]
              }
            ],
            "stackSetId": "eprgxta",
            "stackSetName": "wfbbjnyzrttqqwt",
            "tags": [
              {
                "key": "nske",
                "value": "osigtokfggdb"
              }
            ],
            "templateBody": "clksiqqthzaoksizgbfikwfqlau",
            "templateURL": "yjkkwbrpzenq"
          },
          "publicCloudConnectorsResourceId": "aqrgiomytjqlwcdzmxcebhhwxp",
          "awsAccountId": "dwdxottxkuzhwdcgdvnablsl",
          "arn": "vtteythwslwnjjnzibmkijuvh",
          "publicCloudResourceName": "udz",
          "awsSourceSchema": "ghetqyyzhtyeikecbp",
          "awsRegion": "reoexjnuln",
          "awsTags": {
            "key4760": "ayufgquqqrqznwgsjtxgrplg"
          },
          "provisioningState": "Succeeded"
        },
        "tags": {
          "key3132": "wwcoluqcehfsqmhtamypmejw"
        },
        "location": "zbg",
        "id": "/subscriptions/{subscriptionId}/resourceGroups/{resourceGroupName}/providers/Microsoft.AwsConnector/CloudFormationStackSets/{resourceName}",
        "name": "rtwrlvg",
        "type": "oapobcbnsfhek",
        "systemData": {
          "createdBy": "wgrougdhpxsbwlllkhgylqyz",
          "createdByType": "User",
          "createdAt": "2024-05-13T15:24:50.743Z",
          "lastModifiedBy": "lljqrglsznlclngoh",
          "lastModifiedByType": "User",
          "lastModifiedAt": "2024-05-13T15:24:50.744Z"
        }
      }
    }
  }
}
