{
  "parameters": {
    "accountName": "contosomedia",
    "api-version": "2023-01-01",
    "contentKeyPolicyName": "PolicyWithMultipleOptions",
    "resourceGroupName": "contosorg",
    "subscriptionId": "00000000-0000-0000-0000-000000000000"
  },
  "responses": {
    "200": {
      "body": {
        "description": "A policy with multiple options.",
        "created": "2015-12-01T00:00:00Z",
        "lastModified": "2016-12-02T00:00:00Z",
        "options": [
          {
            "configuration": {
              "@odata.type": "#Microsoft.Media.ContentKeyPolicyClearKeyConfiguration"
            },
            "policyOptionId": "caf1e28c-8288-4301-8c46-c0f9312c512f",
            "restriction": {
              "@odata.type": "#Microsoft.Media.ContentKeyPolicyTokenRestriction",
              "alternateVerificationKeys": [],
              "audience": "urn:test",
              "issuer": "http://testacs",
              "primaryVerificationKey": {
                "@odata.type": "#Microsoft.Media.ContentKeyPolicySymmetricTokenKey",
                "keyValue": "AAA="
              },
              "requiredClaims": [
                {
                  "claimType": "urn:microsoft:azure:mediaservices:contentkeyidentifier"
                },
                {
                  "claimType": "DRM",
                  "claimValue": "Widevine"
                }
              ],
              "restrictionTokenType": "Jwt"
            }
          },
          {
            "configuration": {
              "@odata.type": "#Microsoft.Media.ContentKeyPolicyWidevineConfiguration",
              "widevineTemplate": "{\"allowed_track_types\":\"SD_HD\",\"content_key_specs\":[{\"track_type\":\"SD\",\"security_level\":1,\"required_output_protection\":{\"hdcp\":\"HDCP_V2\"}}],\"policy_overrides\":{\"can_play\":true,\"can_persist\":true,\"can_renew\":false}}"
            },
            "policyOptionId": "da346259-0cd6-4609-89dc-15ac131bd92f",
            "restriction": {
              "@odata.type": "#Microsoft.Media.ContentKeyPolicyOpenRestriction"
            }
          }
        ],
        "policyId": "ed7f3d1b-cfa7-4181-b966-e0b3027eec3a"
      }
    }
  },
  "operationId": "ContentKeyPolicies_GetPolicyPropertiesWithSecrets",
  "title": "Get an Content Key Policy with secrets"
}