{
  "title": "Method to get a Web app data source in site.",
  "operationId": "WebAppDiscoverySiteDataSourceController_GetDataSource",
  "parameters": {
    "api-version": "2022-10-27",
    "subscriptionId": "B22CCABD-8630-4495-8F8C-2F963BB35EEE",
    "resourceGroupName": "rgmigrate",
    "siteName": "ajlsdzwxzpcqvtxrmeag",
    "webAppSiteName": "vltqrholwq",
    "discoverySiteDataSourceName": "mji"
  },
  "responses": {
    "200": {
      "body": {
        "properties": {
          "discoverySiteId": "bmygfjnuwfpxgfhqfvb",
          "provisioningState": "Succeeded"
        },
        "id": "asye",
        "name": "hrbsyiwqlfmaasmrpn",
        "type": "wtdbsph",
        "systemData": {
          "createdBy": "kxxcsgtxbqdryialvcximrsu",
          "createdByType": "User",
          "createdAt": "2023-03-03T13:05:57.834Z",
          "lastModifiedBy": "btxqizobbgwuyogojtxxap",
          "lastModifiedByType": "User",
          "lastModifiedAt": "2023-03-03T13:05:57.834Z"
        }
      }
    }
  }
}