{
  "title": "VcenterController_Get_MaximumSet_Gen - generated by [MaximumSet] rule",
  "operationId": "VcenterController_Get",
  "parameters": {
    "api-version": "2023-06-06",
    "subscriptionId": "1E293F57-6D8B-4B03-BEFB-3A0DBDB27DB4",
    "resourceGroupName": "rgmigrate",
    "siteName": "pX-ifS8n-o6gg--LV62-0hYJ",
    "vcenterName": "22-74-trGN-Q"
  },
  "responses": {
    "200": {
      "body": {
        "properties": {
          "runAsAccountId": "hmslxyd",
          "errors": [
            {
              "message": "iklcloqulevhwwerdbfvulcq",
              "messageParameters": {
                "key3966": "saeoakctzte"
              },
              "applianceName": "akmutodnkzqsdrieiydwewpufj",
              "id": 15,
              "code": "n",
              "possibleCauses": "kimdvhfunficjoqzyuxypgedscwlw",
              "recommendedAction": "tibtmvdejjovgzurwpbsu",
              "severity": "fhwdkxusfabmny",
              "summaryMessage": "xzdqecivmcqauieckmvludyqhqub",
              "source": "RefreshFabricLayout",
              "updatedTimeStamp": "2023-08-19T05:32:30.772Z",
              "runAsAccountId": "rpuvxviliaovujwegykzgdfm",
              "discoveryScope": "AppsAndRoles"
            }
          ],
          "createdTimestamp": "covllekijlqilpzqroldhkpetespwh",
          "updatedTimestamp": "zdofmcqokyx",
          "fqdn": "znakricgbycansrqcvsrkj",
          "port": "uollxeoqigvznwzzpbzbijb",
          "version": "nzzpmbqmgsixfa",
          "perfStatisticsLevel": "ohzjfytvqadsynkuekujkhb",
          "instanceUuid": "hsimxcxsktaxxmvsdvqxxo",
          "friendlyName": "nmtaoyttrob",
          "provisioningState": "Created"
        },
        "id": "yrwxturhtcjfnsvbrajnym",
        "name": "hhyvcbsqjtltzsiak",
        "type": "vmisqibyfdtfftwqrciqgtsvpidxpu",
        "systemData": {
          "createdBy": "mmixpilkalggdyroxukaupd",
          "createdByType": "User",
          "createdAt": "2023-08-19T05:32:16.792Z",
          "lastModifiedBy": "o",
          "lastModifiedByType": "User",
          "lastModifiedAt": "2023-08-19T05:32:16.793Z"
        }
      }
    }
  }
}