{
  "title": "Update_SchemaRegistry",
  "operationId": "SchemaRegistries_Update",
  "description": "Patch a Schema Registry",
  "parameters": {
    "api-version": "2024-09-01-preview",
    "subscriptionId": "00000000-0000-0000-0000-000000000000",
    "resourceGroupName": "myResourceGroup",
    "schemaRegistryName": "my-schema-registry",
    "properties": {
      "properties": {
        "displayName": "Schema Registry namespace 001",
        "description": "This is a sample Schema Registry"
      },
      "tags": {}
    }
  },
  "responses": {
    "200": {
      "body": {
        "id": "/subscriptions/00000000-0000-0000-0000-000000000000/resourceGroups/myResourceGroup/providers/Microsoft.DeviceRegistry/schemaRegistries/my-schema-registry",
        "name": "my-schema-registry",
        "type": "Microsoft.DeviceRegistry/schemaRegistries",
        "tags": {},
        "location": "West Europe",
        "systemData": {
          "createdBy": "2ta23112-4596-44ff-b773-19405922bfc1",
          "createdByType": "Application",
          "createdAt": "2022-11-16T00:36:43.2516899Z",
          "lastModifiedBy": "2ta23112-4596-44ff-b773-19405922bfc1",
          "lastModifiedByType": "Application",
          "lastModifiedAt": "2022-11-16T01:37:16.0922793Z"
        },
        "identity": {
          "principalId": "2ec4560e-5aa0-4bbf-b946-8a238be5b224",
          "tenantId": "61bc9724-77e6-418b-98bb-6b69274cff15",
          "type": "None"
        },
        "properties": {
          "uuid": "0796f7c1-f2c8-44d7-9f5b-9a6f9522a85d",
          "namespace": "sr-namespace-001",
          "displayName": "Schema Registry namespace 001",
          "description": "This is a sample Schema Registry",
          "storageAccountContainerUrl": "my-blob-storage.blob.core.windows.net/my-container",
          "provisioningState": "Succeeded"
        }
      }
    },
    "202": {
      "headers": {
        "Location": "https://contoso.com/operationstatus"
      }
    }
  }
}
