{
  "title": "ScheduledActions_VirtualMachinesCancelOperations - generated by [MinimumSet] rule",
  "operationId": "ScheduledActions_VirtualMachinesCancelOperations",
  "parameters": {
    "api-version": "2025-05-01",
    "subscriptionId": "7EA018A3-C331-40FB-9A0D-DDD9FB4FDEF5",
    "locationparameter": "ocnllijfnjhgvastvdyjzjbk",
    "requestBody": {
      "operationIds": [
        "lmgwkjlng"
      ],
      "correlationid": "vhgqpkvmxkzusevudcelljti"
    }
  },
  "responses": {
    "200": {
      "body": {
        "results": [
          {}
        ]
      }
    }
  }
}
